topsis_101903169/__init__.py
topsis_101903169/topsis.py
topsis_101903169-2.1.0.dist-info/LICENSE
topsis_101903169-2.1.0.dist-info/METADATA
topsis_101903169-2.1.0.dist-info/WHEEL
topsis_101903169-2.1.0.dist-info/top_level.txt
topsis_101903169-2.1.0.dist-info/RECORD
