Metadata-Version: 2.1
Name: topsis-101903169
Version: 2.1.0
Summary: topsis
Home-page: UNKNOWN
Author: Parmeet Singh
Author-email: parmeet845@gmail.com
License: MIT
Platform: UNKNOWN
Classifier: License :: OSI Approved :: MIT License
Classifier: Programming Language :: Python :: 3
Classifier: Programming Language :: Python :: 3.7
